{
  "dtrack-s3" : {
    "Type" : "SimpleFolder",
    "ControlmServer" : "ctmaws",
    "OrderMethod" : "Manual",
    "instanceToS3" : {
      "Type" : "Job:FileTransfer",
      "ConnectionProfileSrc" : "neilcOnLocal",
      "ConnectionProfileDest" : "ncus3",
      "SubApplication" : "ncuaws",
      "EndFolder" : true,
      "Host" : "ncuctm",
      "CreatedBy" : "emuser",
      "Description" : "File Transfer to S3",
      "RunAs" : "neilcOnLocal+ncus3",
      "Application" : "aws",
      "Variables" : [ {
        "FTP-RHOST" : "S3"
      }, {
        "FTP-LOSTYPE" : "Unix"
      }, {
        "FTP-CONNTYPE1" : "LOCAL"
      }, {
        "FTP-LHOST" : "Local"
      }, {
        "FTP-LUSER" : "neilc"
      }, {
        "FTP-HOMEDIR1" : "/home/neilc/"
      }, {
        "FTP-ROSTYPE" : "Unix"
      }, {
        "FTP-CONNTYPE2" : "S3"
      }, {
        "FTP-HOMEDIR2" : "/"
      }, {
        "FTP-S3_BUCKET_NAME" : "ncu-schumi"
      }, {
        "FTP-CM_VER" : "9.0.00"
      }, {
        "FTP-TIMELIMIT_UNIT1" : "1"
      } ],
      "FileTransfers" : [ {
        "TransferType" : "Binary",
        "TransferOption" : "SrcToDest",
        "Src" : "/home/neilc/ctmsoft/v19/agv19/DRKAI.9.0.19.000_Linux-x86_64.tar.Z",
        "Dest" : "/controlm/",
        "ABSTIME" : "0",
        "TIMELIMIT" : "0",
        "UNIQUE" : "0",
        "SRCOPT" : "0",
        "IF_EXIST" : "0",
        "DSTOPT" : "0",
        "RECURSIVE" : "0",
        "EXCLUDE_WILDCARD" : "0",
        "TRIM" : "1",
        "NULLFLDS" : "0",
        "VERNUM" : "0",
        "CASEIFS" : "0"
      } ],
      "When" : {
        "WeekDays" : [ "NONE" ],
        "MonthDays" : [ "NONE" ],
        "SpecificDates" : [ ],
        "DaysRelation" : "OR"
      }
    }
  }
}
